quantfinpy/__init__.py
quantfinpy/data/__init__.py
quantfinpy/data/cashflow/__init__.py
quantfinpy/data/cashflow/cashflow.py
quantfinpy/data/cashflow/schedule.py
quantfinpy/data/ir/__init__.py
quantfinpy/data/ir/cashflow.py
quantfinpy/data/ir/curve.py
quantfinpy/data/tenor.py
quantfinpy/enum/__init__.py
quantfinpy/enum/currency.py
quantfinpy/enum/ir_index.py
quantfinpy/instrument/__init__.py
quantfinpy/instrument/credit/__init__.py
quantfinpy/instrument/credit/bond.py
quantfinpy/instrument/credit/cds.py
quantfinpy/instrument/credit/instrument.py
quantfinpy/instrument/equity/__init__.py
quantfinpy/instrument/equity/share.py
quantfinpy/instrument/forward.py
quantfinpy/instrument/fx/__init__.py
quantfinpy/instrument/fx/forward.py
quantfinpy/instrument/fx/spot.py
quantfinpy/instrument/index.py
quantfinpy/instrument/instrument.py
quantfinpy/instrument/ir/__init__.py
quantfinpy/instrument/ir/cashflow/__init__.py
quantfinpy/instrument/ir/cashflow/schedule.py
quantfinpy/instrument/ir/swap/__init__.py
quantfinpy/instrument/ir/swap/fixed_fixed.py
quantfinpy/instrument/ir/swap/fixed_float.py
quantfinpy/instrument/ir/swap/fixed_leg.py
quantfinpy/instrument/ir/swap/floating_leg.py
quantfinpy/instrument/ir/swap/mixin.py
quantfinpy/instrument/option.py
quantfinpy/instrument/portfolio.py
quantfinpy/instrument/spot.py
quantfinpy/instrument/swap.py
quantfinpy/order/__init__.py
quantfinpy/order/limit.py
quantfinpy/order/market.py
quantfinpy/order/order.py
quantfinpy/order/stop.py
quantfinpy/order/stop_limit.py
quantfinpy/utils/__init__.py
quantfinpy/utils/abc.py
quantfinpy/utils/itertools.py
quantfinpy/utils/schedule.py
quantfinpy/utils/sort.py
quantfinpy-0.0.3.dist-info/LICENSE
quantfinpy-0.0.3.dist-info/WHEEL
quantfinpy-0.0.3.dist-info/METADATA
quantfinpy-0.0.3.dist-info/RECORD
